qmi/__init__.py
qmi/py.typed
qmi/core/__init__.py
qmi/core/config.py
qmi/core/config_defs.py
qmi/core/config_struct.py
qmi/core/context.py
qmi/core/context_singleton.py
qmi/core/exceptions.py
qmi/core/instrument.py
qmi/core/logging_init.py
qmi/core/messaging.py
qmi/core/object_registry.py
qmi/core/pubsub.py
qmi/core/read_keyboard.py
qmi/core/rpc.py
qmi/core/scpi_protocol.py
qmi/core/task.py
qmi/core/thread.py
qmi/core/transport.py
qmi/core/transport_gpib_visa.py
qmi/core/transport_usbtmc_pyusb.py
qmi/core/transport_usbtmc_visa.py
qmi/core/udp_responder_packets.py
qmi/core/usbtmc.py
qmi/core/util.py
qmi/data/__init__.py
qmi/data/dataset.py
qmi/data/datastore.py
qmi/data/hdf5recorder.py
qmi/instruments/__init__.py
qmi/instruments/adwin/__init__.py
qmi/instruments/adwin/adwin.py
qmi/instruments/adwin/goldii.py
qmi/instruments/adwin/proii.py
qmi/instruments/agiltron/__init__.py
qmi/instruments/agiltron/_ff_optical_switch.py
qmi/instruments/agiltron/ff1x4.py
qmi/instruments/agiltron/ff1x8.py
qmi/instruments/anapico/__init__.py
qmi/instruments/anapico/apsin.py
qmi/instruments/aviosys/__init__.py
qmi/instruments/aviosys/ippower.py
qmi/instruments/boston_micromachines/__init__.py
qmi/instruments/boston_micromachines/multidm.py
qmi/instruments/bristol/__init__.py
qmi/instruments/bristol/bristol_871a.py
qmi/instruments/bristol/fos.py
qmi/instruments/cobolt/__init__.py
qmi/instruments/cobolt/laser_06_01.py
qmi/instruments/digilent/__init__.py
qmi/instruments/digilent/analog_discovery.py
qmi/instruments/dummy/__init__.py
qmi/instruments/dummy/noisy_sine_generator.py
qmi/instruments/edwards/__init__.py
qmi/instruments/edwards/turbo_instrument_controller.py
qmi/instruments/high_finesse/__init__.py
qmi/instruments/high_finesse/wlm.py
qmi/instruments/high_finesse/support/__init__.py
qmi/instruments/high_finesse/support/_library_wrapper.py
qmi/instruments/high_finesse/support/wlmConst.py
qmi/instruments/high_finesse/support/wlmData.py
qmi/instruments/imagine_eyes/__init__.py
qmi-0.51.1.dist-info/licenses/LICENSE.md
qmi-0.51.1.dist-info/METADATA
qmi-0.51.1.dist-info/WHEEL
qmi-0.51.1.dist-info/entry_points.txt
qmi-0.51.1.dist-info/top_level.txt
qmi-0.51.1.dist-info/RECORD
