Metadata-Version: 2.4
Name: qmi
Version: 0.51.1
Summary: The Quantum Measurement Infrastructure framework
Author-email: QuTech <F.J.Grooteman@tudelft.nl>
License: Technische Universiteit Delft hereby disclaims all copyright interest in the program “QMI (Quantum Measurement Infrastructure)”, a lab instrument remote procedure call control framework written by QuTech. 
Project-URL: Homepage, https://github.com/QuTech-Delft/QMI
Project-URL: Repository, https://github.com/QuTech-Delft/QMI.git
Project-URL: Changelog, https://github.com/QuTech-Delft/QMI/blob/stable-0-51/CHANGELOG.md
Project-URL: Issues, https://github.com/QuTech-Delft/QMI/issues
Keywords: qmi,hardware,software,interface,laboratory,physics
Classifier: Development Status :: 4 - Beta
Classifier: Intended Audience :: Science/Research
Classifier: Operating System :: Unix
Classifier: Operating System :: POSIX
Classifier: Operating System :: Microsoft :: Windows
Classifier: Programming Language :: Python
Classifier: Programming Language :: Python :: 3
Classifier: Programming Language :: Python :: 3.11
Classifier: Programming Language :: Python :: 3.12
Classifier: Programming Language :: Python :: 3.13
Classifier: Programming Language :: Python :: Implementation :: CPython
Classifier: Programming Language :: Python :: Implementation :: PyPy
Classifier: Topic :: Scientific/Engineering :: Physics
Classifier: Natural Language :: English
Requires-Python: <4,>=3.11
License-File: LICENSE.md
Requires-Dist: setuptools
Requires-Dist: wheel
Requires-Dist: twine
Requires-Dist: numpy
Requires-Dist: scipy
Requires-Dist: h5py>=3.7.0
Requires-Dist: pyserial
Requires-Dist: pyusb
Requires-Dist: python-vxi11
Requires-Dist: pytz
Requires-Dist: psutil
Requires-Dist: colorama
Requires-Dist: jsonschema
Requires-Dist: pydwf
Provides-Extra: dev
Requires-Dist: setuptools; extra == "dev"
Requires-Dist: wheel; extra == "dev"
Requires-Dist: twine; extra == "dev"
Requires-Dist: astroid; extra == "dev"
Requires-Dist: coverage; extra == "dev"
Requires-Dist: pylint>=3.0; extra == "dev"
Requires-Dist: mypy; extra == "dev"
Requires-Dist: sphinx; extra == "dev"
Requires-Dist: sphinx_rtd_theme; extra == "dev"
Requires-Dist: bump2version; extra == "dev"
Dynamic: license-file
